withpi/__init__.py
withpi/_base_client.py
withpi/_client.py
withpi/_compat.py
withpi/_constants.py
withpi/_exceptions.py
withpi/_files.py
withpi/_models.py
withpi/_qs.py
withpi/_resource.py
withpi/_response.py
withpi/_streaming.py
withpi/_types.py
withpi/_version.py
withpi/py.typed
withpi/_utils/__init__.py
withpi/_utils/_compat.py
withpi/_utils/_datetime_parse.py
withpi/_utils/_logs.py
withpi/_utils/_proxy.py
withpi/_utils/_reflection.py
withpi/_utils/_resources_proxy.py
withpi/_utils/_streams.py
withpi/_utils/_sync.py
withpi/_utils/_transform.py
withpi/_utils/_typing.py
withpi/_utils/_utils.py
withpi/lib/.keep
withpi/resources/__init__.py
withpi/resources/data/__init__.py
withpi/resources/data/data.py
withpi/resources/data/generate.py
withpi/resources/data/generate_input_response_pairs.py
withpi/resources/scoring_system/__init__.py
withpi/resources/scoring_system/calibrate.py
withpi/resources/scoring_system/generate.py
withpi/resources/scoring_system/scoring_system.py
withpi/resources/search/__init__.py
withpi/resources/search/consistency.py
withpi/resources/search/groundedness.py
withpi/resources/search/search.py
withpi/types/__init__.py
withpi/types/scoring_system_score_params.py
withpi/types/search_embed_params.py
withpi/types/search_embed_response.py
withpi/types/search_rank_params.py
withpi/types/search_rank_response.py
withpi/types/data/__init__.py
withpi/types/data/generate_cancel_response.py
withpi/types/data/generate_input_response_pair_cancel_response.py
withpi/types/data/generate_input_response_pair_list_params.py
withpi/types/data/generate_input_response_pair_list_response.py
withpi/types/data/generate_input_response_pair_start_job_params.py
withpi/types/data/generate_input_response_pair_stream_data_response.py
withpi/types/data/generate_input_response_pair_stream_messages_response.py
withpi/types/data/generate_list_params.py
withpi/types/data/generate_list_response.py
withpi/types/data/generate_start_job_params.py
withpi-1.78.3.dist-info/METADATA
withpi-1.78.3.dist-info/WHEEL
withpi-1.78.3.dist-info/licenses/LICENSE
withpi-1.78.3.dist-info/RECORD
